openai_tts_mcp_server/__init__.py
openai_tts_mcp_server/ding.aiff
openai_tts_mcp_server/server.py
openai_tts_mcp_server-0.1.3.dist-info/METADATA
openai_tts_mcp_server-0.1.3.dist-info/WHEEL
openai_tts_mcp_server-0.1.3.dist-info/entry_points.txt
openai_tts_mcp_server-0.1.3.dist-info/RECORD
