Metadata-Version: 2.4
Name: openai-tts-mcp-server
Version: 0.1.3
Summary: An MCP server integrating with OpenAI TTS (text-to-speech) API
Author-email: Tomek Korbak <tomasz.korbak@gmail.com>
Requires-Python: >=3.12
Requires-Dist: mcp>=1.5.0
Requires-Dist: openai>=1.68.2
Requires-Dist: pydub>=0.25.1
